{"title":"SNU 팩트체크 ─ 네이버 뉴스 ─ 20대 대선","url":"https://m.news.naver.com/factcheck/main?section=20%EB%8C%80+%EB%8C%80%ED%86%B5%EB%A0%B9+%EC%84%A0%EA%B1%B0","favicon":"https://m.news.naver.com/factcheck/favicon.ico","elements":[{"title":"윤석열·이재명 양자토론은 법 위반이다","contents":"대체로 사실","link":"https://m.news.naver.com/factcheck/end?id=3706","retrieved":1643011759498},{"title":"19대 대통령 선거에서 문재인 대통령 지지율은 40%를 못 넘었다","contents":"전혀 사실 아님","link":"https://m.news.naver.com/factcheck/end?id=3715","retrieved":1643101510318},{"title":"이재명 욕설 파일을 일부 발췌해 지상파에서 방송하는 것은 선거법 위반이다","contents":"대체로 사실이 아님","link":"https://m.news.naver.com/factcheck/end?id=3714","retrieved":1643101510320},{"title":"주택 311만 호 공급 가능하다","contents":"대체로 사실이 아님","link":"https://m.news.naver.com/factcheck/end?id=3712","retrieved":1643094380895},{"title":"외국인은 담보대출비율 100%, 대한민국 국민은 40%","contents":"대체로 사실이 아님","link":"https://m.news.naver.com/factcheck/end?id=3708","retrieved":1643011759497},{"title":"임대차3법은 사실 베를린을 포함한 여러 선진국에서 실패한 사례가 굉장히 많은 법이다","contents":"대체로 사실이 아님","link":"https://m.news.naver.com/factcheck/end?id=3704","retrieved":1643011759498},{"title":"현재 대한민국 국회의원 평균 연령이 55.5세이다","contents":"대체로 사실","link":"https://m.news.naver.com/factcheck/end?id=3705","retrieved":1643011759500},{"title":"실내에서 마스크를 착용하고 대화를 하지 않는 경우 코로나 바이러스 전파 가능성이 매우 낮다","contents":"대체로 사실","link":"https://m.news.naver.com/factcheck/end?id=3703","retrieved":1643011759501},{"title":"전 세계에서 완전봉쇄 없이 이 정도 방역 성과를 내는 나라는 우리나라밖에 없다","contents":"대체로 사실","link":"https://m.news.naver.com/factcheck/end?id=3702","retrieved":1643011759502},{"title":"대한민국 구조대의 탐색구조능력은 세계 최고 수준이다","contents":"대체로 사실","link":"https://m.news.naver.com/factcheck/end?id=3700","retrieved":1642752448433}]}