{"title":"SNU 팩트체크 ─ 네이버 뉴스","url":"https://m.news.naver.com/factcheck/main","favicon":"https://m.news.naver.com/factcheck/favicon.ico","elements":[{"title":"영국 왕족 여성만 장례식장에서 검은 망사 모자를 쓴다","contents":"대체로 사실이 아님","link":"https://m.news.naver.com/factcheck/end?id=4401","retrieved":1663748123843},{"title":"국내 전기차 보조금, 테슬라가 싹쓸이했다","contents":"전혀 사실 아님","link":"https://m.news.naver.com/factcheck/end?id=4399","retrieved":1663731809823},{"title":"'음료 든 컵 들고 버스 탑승 금지' 법적 근거 없다","contents":"전혀 사실 아님","link":"https://m.news.naver.com/factcheck/end?id=4398","retrieved":1663661546338},{"title":"‘자이언트 스텝’·‘울트라 스텝’은 한국산 용어다","contents":"사실","link":"https://m.news.naver.com/factcheck/end?id=4396","retrieved":1663575360484},{"title":"조선족은 은행 ATM 수수료 면제 받는다","contents":"전혀 사실 아님","link":"https://m.news.naver.com/factcheck/end?id=4395","retrieved":1663575360485}]}